{"namespace":"UNIODesignSystem_50cc4d","components":[],"startingPoints":[],"cards":[{"path":"preview/comp-benchmark.html","group":"Components","viewport":"700x230","subtitle":"NOVA accuracy vs. market average","name":"Benchmark line"},{"path":"preview/comp-besichtigung.html","group":"Components","viewport":"700x430","subtitle":"Live viewing table — score rings + probability","name":"Besichtigungsstatus"},{"path":"preview/comp-channel.html","group":"Components","viewport":"700x430","subtitle":"Acquisition channels · bars + cost-per-lead","name":"Channel Performance"},{"path":"preview/comp-einheiten.html","group":"Components","viewport":"700x420","subtitle":"Unit demand table — status, demand, A/B/C qual","name":"Einheiten & Nachfrage"},{"path":"preview/comp-forecast.html","group":"Components","viewport":"700x330","subtitle":"Umsatz-Forecast — high/low bars, Verkauf vs. Prognose","name":"Forecast chart"},{"path":"preview/comp-funnel.html","group":"Components","viewport":"700x500","subtitle":"Lead→Angebot funnel, orange→green scale + conversion","name":"Marketing Funnel"},{"path":"preview/comp-gauge.html","group":"Components","viewport":"700x250","subtitle":"Project score rings with status + delta","name":"Gauge cards"},{"path":"preview/comp-hightech.html","group":"Components","viewport":"700x300","subtitle":"Palantir-style instrumentation — console, crosshair, brackets, scan","name":"High-Tech Elemente"},{"path":"preview/comp-map.html","group":"Components","viewport":"1000x548","subtitle":"Standort-Karte — pins, cluster, toolbar, project panel","name":"Lage-Karte"},{"path":"preview/comp-progress.html","group":"Components","viewport":"700x250","subtitle":"Segmented + solid progress KPI cards","name":"Progress / breakdown"},{"path":"preview/comp-rings.html","group":"Components","viewport":"700x340","subtitle":"Gauge, segmented donut & activity rings built on the UNIO ring form","name":"Ring-Diagramme"},{"path":"preview/comp-sparktrio.html","group":"Components","viewport":"700x150","subtitle":"KPI trio with mini bar sparklines","name":"Sparkline KPIs"},{"path":"ui_kits/data_story/index.html","group":"UI Kit — Data Story","viewport":"1100x648","subtitle":"Looping data-point animation: Sammeln → Lernen → Optimieren → Verkaufen","name":"Data Story (animated)"},{"path":"ui_kits/data_story/network.html","group":"UI Kit — Data Story","viewport":"1100x560","subtitle":"Animated data-point network + reusable node/link style motifs","name":"Datenvernetzung"},{"path":"ui_kits/homepage/index.html","group":"UI Kit — Homepage","viewport":"1240x760","subtitle":"Dark, data-driven homepage — hero + live dashboard, products, process, CTA","name":"Homepage redesign"},{"path":"ui_kits/lens_dashboard/index.html","group":"UI Kit — Lens Dashboard","viewport":"1440x820","subtitle":"Data-intelligence console — KPIs, demand chart, unit donut, pipeline table","name":"LENS dashboard"}],"globalCssPaths":["colors_and_type.css"],"tokens":[{"name":"--font-display","value":"'Host Grotesk', system-ui, -apple-system, sans-serif","kind":"font","definedIn":"colors_and_type.css"},{"name":"--font-sans","value":"'Host Grotesk', system-ui, -apple-system, sans-serif","kind":"font","definedIn":"colors_and_type.css"},{"name":"--font-mono","value":"'Host Grotesk', system-ui, sans-serif","kind":"font","definedIn":"colors_and_type.css"},{"name":"--orange","value":"#FFAA09","kind":"color","definedIn":"colors_and_type.css"},{"name":"--orange-bright","value":"#FFC24D","kind":"color","definedIn":"colors_and_type.css"},{"name":"--orange-press","value":"#E89200","kind":"color","definedIn":"colors_and_type.css"},{"name":"--orange-deep","value":"#C77F00","kind":"color","definedIn":"colors_and_type.css"},{"name":"--yellow","value":"#FFC53D","kind":"color","definedIn":"colors_and_type.css"},{"name":"--orange-wash","value":"#FFF3DD","kind":"color","definedIn":"colors_and_type.css"},{"name":"--bg-base","value":"#FFFFFF","kind":"color","definedIn":"colors_and_type.css"},{"name":"--bg-soft","value":"#F4F4F2","kind":"color","definedIn":"colors_and_type.css"},{"name":"--surface-1","value":"#F5F5F3","kind":"color","definedIn":"colors_and_type.css"},{"name":"--surface-2","value":"#FFFFFF","kind":"color","definedIn":"colors_and_type.css"},{"name":"--surface-3","value":"#ECECE8","kind":"color","definedIn":"colors_and_type.css"},{"name":"--surface-4","value":"#E4E4DF","kind":"color","definedIn":"colors_and_type.css"},{"name":"--border-faint","value":"rgba(20,20,18,0.05)","kind":"color","definedIn":"colors_and_type.css"},{"name":"--border","value":"rgba(20,20,18,0.09)","kind":"color","definedIn":"colors_and_type.css"},{"name":"--border-strong","value":"rgba(20,20,18,0.16)","kind":"color","definedIn":"colors_and_type.css"},{"name":"--grid-line","value":"rgba(20,20,18,0.04)","kind":"color","definedIn":"colors_and_type.css"},{"name":"--fg-1","value":"#18191B","kind":"color","definedIn":"colors_and_type.css"},{"name":"--fg-2","value":"#5C5E62","kind":"color","definedIn":"colors_and_type.css"},{"name":"--fg-3","value":"#97999D","kind":"color","definedIn":"colors_and_type.css"},{"name":"--fg-4","value":"#C3C4C6","kind":"color","definedIn":"colors_and_type.css"},{"name":"--on-orange","value":"#1A1305","kind":"color","definedIn":"colors_and_type.css"},{"name":"--pos","value":"#C8920A","kind":"color","definedIn":"colors_and_type.css"},{"name":"--pos-dim","value":"rgba(230,154,9,0.12)","kind":"color","definedIn":"colors_and_type.css"},{"name":"--neg","value":"#9BA0AA","kind":"color","definedIn":"colors_and_type.css"},{"name":"--neg-dim","value":"rgba(224,72,61,0.10)","kind":"color","definedIn":"colors_and_type.css"},{"name":"--warn","value":"#E8920A","kind":"color","definedIn":"colors_and_type.css"},{"name":"--info","value":"#9BA0AA","kind":"color","definedIn":"colors_and_type.css"},{"name":"--violet","value":"#9BA0AA","kind":"color","definedIn":"colors_and_type.css"},{"name":"--c-orange","value":"#FFAA09","kind":"color","definedIn":"colors_and_type.css"},{"name":"--c-yellow","value":"#FFD24D","kind":"color","definedIn":"colors_and_type.css"},{"name":"--c-gold","value":"#C8920A","kind":"color","definedIn":"colors_and_type.css"},{"name":"--c-green","value":"#C8920A","kind":"color","definedIn":"colors_and_type.css"},{"name":"--c-blue","value":"#9BA0AA","kind":"color","definedIn":"colors_and_type.css"},{"name":"--c-teal","value":"#C8920A","kind":"color","definedIn":"colors_and_type.css"},{"name":"--c-pink","value":"#FFAA09","kind":"color","definedIn":"colors_and_type.css"},{"name":"--c-red","value":"#9BA0AA","kind":"color","definedIn":"colors_and_type.css"},{"name":"--c-gray","value":"#9BA0AA","kind":"color","definedIn":"colors_and_type.css"},{"name":"--score-hi","value":"#C8920A","kind":"color","definedIn":"colors_and_type.css"},{"name":"--score-mid","value":"#F5A623","kind":"color","definedIn":"colors_and_type.css"},{"name":"--score-lo","value":"#E8C24A","kind":"color","definedIn":"colors_and_type.css"},{"name":"--qual-a-bg","value":"#FFF3DD","kind":"color","definedIn":"colors_and_type.css"},{"name":"--qual-a-fg","value":"#B7791F","kind":"color","definedIn":"colors_and_type.css"},{"name":"--qual-b-bg","value":"#FEF3D6","kind":"color","definedIn":"colors_and_type.css"},{"name":"--qual-b-fg","value":"#C77F00","kind":"color","definedIn":"colors_and_type.css"},{"name":"--qual-c-bg","value":"#F1F2F4","kind":"color","definedIn":"colors_and_type.css"},{"name":"--qual-c-fg","value":"#82868D","kind":"color","definedIn":"colors_and_type.css"},{"name":"--st-green-bg","value":"#FFF3DD","kind":"color","definedIn":"colors_and_type.css"},{"name":"--st-green-fg","value":"#B7791F","kind":"color","definedIn":"colors_and_type.css"},{"name":"--st-blue-bg","value":"#F1F2F4","kind":"color","definedIn":"colors_and_type.css"},{"name":"--st-blue-fg","value":"#6E727A","kind":"color","definedIn":"colors_and_type.css"},{"name":"--st-amber-bg","value":"#FFF3DD","kind":"color","definedIn":"colors_and_type.css"},{"name":"--st-amber-fg","value":"#B7791F","kind":"color","definedIn":"colors_and_type.css"},{"name":"--st-hot-bg","value":"#FFEAD2","kind":"color","definedIn":"colors_and_type.css"},{"name":"--st-hot-fg","value":"#D9760A","kind":"color","definedIn":"colors_and_type.css"},{"name":"--st-cold-bg","value":"#EEF0F2","kind":"color","definedIn":"colors_and_type.css"},{"name":"--st-cold-fg","value":"#7A8089","kind":"color","definedIn":"colors_and_type.css"},{"name":"--st-ink-bg","value":"#18191B","kind":"color","definedIn":"colors_and_type.css"},{"name":"--st-ink-fg","value":"#FFFFFF","kind":"color","definedIn":"colors_and_type.css"},{"name":"--chip-amber-bg","value":"#FEF3D6","kind":"color","definedIn":"colors_and_type.css"},{"name":"--chip-amber-fg","value":"#C77F00","kind":"color","definedIn":"colors_and_type.css"},{"name":"--chip-blue-bg","value":"#F1F2F4","kind":"color","definedIn":"colors_and_type.css"},{"name":"--chip-blue-fg","value":"#6E727A","kind":"color","definedIn":"colors_and_type.css"},{"name":"--chip-teal-bg","value":"#FFF6E6","kind":"color","definedIn":"colors_and_type.css"},{"name":"--chip-teal-fg","value":"#C8920A","kind":"color","definedIn":"colors_and_type.css"},{"name":"--chip-green-bg","value":"#FFF3DD","kind":"color","definedIn":"colors_and_type.css"},{"name":"--chip-green-fg","value":"#B7791F","kind":"color","definedIn":"colors_and_type.css"},{"name":"--chip-red-bg","value":"#F1F2F4","kind":"color","definedIn":"colors_and_type.css"},{"name":"--chip-red-fg","value":"#82868D","kind":"color","definedIn":"colors_and_type.css"},{"name":"--chart-line","value":"#C7C8C4","kind":"color","definedIn":"colors_and_type.css"},{"name":"--chart-track","value":"#E9E9E5","kind":"color","definedIn":"colors_and_type.css"},{"name":"--chart-grid","value":"rgba(20,20,18,0.05)","kind":"color","definedIn":"colors_and_type.css"},{"name":"--chart-accent","value":"var(--orange)","kind":"color","definedIn":"colors_and_type.css"},{"name":"--r-xs","value":"6px","kind":"spacing","definedIn":"colors_and_type.css"},{"name":"--r-sm","value":"10px","kind":"spacing","definedIn":"colors_and_type.css"},{"name":"--r-md","value":"14px","kind":"spacing","definedIn":"colors_and_type.css"},{"name":"--r-lg","value":"18px","kind":"spacing","definedIn":"colors_and_type.css"},{"name":"--r-xl","value":"24px","kind":"spacing","definedIn":"colors_and_type.css"},{"name":"--r-pill","value":"999px","kind":"spacing","definedIn":"colors_and_type.css"},{"name":"--s-1","value":"4px","kind":"spacing","definedIn":"colors_and_type.css"},{"name":"--s-2","value":"8px","kind":"spacing","definedIn":"colors_and_type.css"},{"name":"--s-3","value":"12px","kind":"spacing","definedIn":"colors_and_type.css"},{"name":"--s-4","value":"16px","kind":"spacing","definedIn":"colors_and_type.css"},{"name":"--s-5","value":"24px","kind":"spacing","definedIn":"colors_and_type.css"},{"name":"--s-6","value":"32px","kind":"spacing","definedIn":"colors_and_type.css"},{"name":"--s-7","value":"48px","kind":"spacing","definedIn":"colors_and_type.css"},{"name":"--s-8","value":"64px","kind":"spacing","definedIn":"colors_and_type.css"},{"name":"--s-9","value":"96px","kind":"spacing","definedIn":"colors_and_type.css"},{"name":"--s-10","value":"128px","kind":"spacing","definedIn":"colors_and_type.css"},{"name":"--shadow-1","value":"0 1px 2px rgba(20,20,18,0.05)","kind":"shadow","definedIn":"colors_and_type.css"},{"name":"--shadow-2","value":"0 4px 18px -4px rgba(20,20,18,0.10)","kind":"shadow","definedIn":"colors_and_type.css"},{"name":"--shadow-3","value":"0 18px 48px -16px rgba(20,20,18,0.16)","kind":"shadow","definedIn":"colors_and_type.css"},{"name":"--glow-orange","value":"0 6px 22px -6px rgba(255,170,9,0.45)","kind":"shadow","definedIn":"colors_and_type.css"},{"name":"--ease-out","value":"cubic-bezier(0.16,1,0.3,1)","kind":"other","definedIn":"colors_and_type.css"},{"name":"--ease-in-out","value":"cubic-bezier(0.65,0,0.35,1)","kind":"other","definedIn":"colors_and_type.css"},{"name":"--dur-1","value":"120ms","kind":"other","definedIn":"colors_and_type.css"},{"name":"--dur-2","value":"220ms","kind":"other","definedIn":"colors_and_type.css"},{"name":"--dur-3","value":"400ms","kind":"other","definedIn":"colors_and_type.css"},{"name":"--dur-4","value":"700ms","kind":"other","definedIn":"colors_and_type.css"}],"themes":[],"fonts":[],"brandFonts":[{"family":"Host Grotesk","status":"ok","tokens":["--font-display","--font-sans","--font-mono"],"path":"colors_and_type.css"}],"source":"spa"}